v_ft/__init__.py
v_ft/custom_primitives.py
v_ft/load.py
v_ft/time_unit.py
v_ft/data/ft_case2case.json
v_ft/data/ft_case2entity.json
v_ft/data/ft_case2entity_window .json
v_ft/data/ft_rec2case.json
v_ft-0.1.0.dist-info/LICENSE
v_ft-0.1.0.dist-info/METADATA
v_ft-0.1.0.dist-info/WHEEL
v_ft-0.1.0.dist-info/top_level.txt
v_ft-0.1.0.dist-info/RECORD
