Metadata-Version: 2.1
Name: v-ft
Version: 0.1.0
Summary: featuretools related extensions
Home-page: https://github.com/jeremite/ft_extension
Author: Travis_li
Author-email: wli10@email.wm.edu
License: UNKNOWN
Platform: UNKNOWN
Classifier: Programming Language :: Python :: 3
Classifier: License :: OSI Approved :: MIT License
Classifier: Operating System :: OS Independent
Requires-Python: >=3.6
